pigar/.db.sqlite3
pigar/__init__.py
pigar/__main__.py
pigar/core.py
pigar/db.py
pigar/dist.py
pigar/helpers.py
pigar/log.py
pigar/parser.py
pigar/unpack.py
pigar/version.py
pigar/_vendor/README.md
pigar/_vendor/__init__.py
pigar/_vendor/vendor.txt
pigar/_vendor/pip/LICENSE.txt
pigar/_vendor/pip/__init__.py
pigar/_vendor/pip/__main__.py
pigar/_vendor/pip/__pip-runner__.py
pigar/_vendor/pip/py.typed
pigar/_vendor/pip/_internal/__init__.py
pigar/_vendor/pip/_internal/build_env.py
pigar/_vendor/pip/_internal/cache.py
pigar/_vendor/pip/_internal/configuration.py
pigar/_vendor/pip/_internal/exceptions.py
pigar/_vendor/pip/_internal/main.py
pigar/_vendor/pip/_internal/pyproject.py
pigar/_vendor/pip/_internal/self_outdated_check.py
pigar/_vendor/pip/_internal/wheel_builder.py
pigar/_vendor/pip/_internal/cli/__init__.py
pigar/_vendor/pip/_internal/cli/autocompletion.py
pigar/_vendor/pip/_internal/cli/base_command.py
pigar/_vendor/pip/_internal/cli/cmdoptions.py
pigar/_vendor/pip/_internal/cli/command_context.py
pigar/_vendor/pip/_internal/cli/index_command.py
pigar/_vendor/pip/_internal/cli/main.py
pigar/_vendor/pip/_internal/cli/main_parser.py
pigar/_vendor/pip/_internal/cli/parser.py
pigar/_vendor/pip/_internal/cli/progress_bars.py
pigar/_vendor/pip/_internal/cli/req_command.py
pigar/_vendor/pip/_internal/cli/spinners.py
pigar/_vendor/pip/_internal/cli/status_codes.py
pigar/_vendor/pip/_internal/commands/__init__.py
pigar/_vendor/pip/_internal/commands/cache.py
pigar/_vendor/pip/_internal/commands/check.py
pigar/_vendor/pip/_internal/commands/completion.py
pigar/_vendor/pip/_internal/commands/configuration.py
pigar/_vendor/pip/_internal/commands/debug.py
pigar/_vendor/pip/_internal/commands/download.py
pigar/_vendor/pip/_internal/commands/freeze.py
pigar/_vendor/pip/_internal/commands/hash.py
pigar/_vendor/pip/_internal/commands/help.py
pigar/_vendor/pip/_internal/commands/index.py
pigar/_vendor/pip/_internal/commands/inspect.py
pigar-2.1.6.dist-info/LICENSE
pigar-2.1.6.dist-info/LICENSE.txt
pigar-2.1.6.dist-info/METADATA
pigar-2.1.6.dist-info/WHEEL
pigar-2.1.6.dist-info/entry_points.txt
pigar-2.1.6.dist-info/top_level.txt
pigar-2.1.6.dist-info/RECORD
