Metadata-Version: 2.1
Name: pigar
Version: 2.1.6
Summary: A tool to generate requirements.txt for Python project.
Author-email: damnever <the.xcdong@gmail.com>
License: BSD 3-Clause License
Project-URL: Documentation, https://github.com/damnever/pigar
Project-URL: Source, https://github.com/damnever/pigar
Keywords: requirements.txt,automation,tool,module-search
Classifier: Development Status :: 5 - Production/Stable
Classifier: Intended Audience :: Developers
Classifier: Topic :: Utilities
Classifier: License :: OSI Approved :: BSD License
Classifier: Programming Language :: Python :: Implementation :: CPython
Classifier: Programming Language :: Python :: 3 :: Only
Classifier: Programming Language :: Python :: 3.8
Classifier: Programming Language :: Python :: 3.9
Classifier: Programming Language :: Python :: 3.10
Classifier: Programming Language :: Python :: 3.11
Classifier: Programming Language :: Python :: 3.12
Requires-Python: >=3.8
License-File: LICENSE
License-File: pigar/_vendor/pip/LICENSE.txt
Requires-Dist: click>=8.1
Requires-Dist: nbformat>=5.7
Requires-Dist: aiohttp>=3.9
Requires-Dist: colorama
